pymethyl2sam/__init__.py
pymethyl2sam/core/__init__.py
pymethyl2sam/core/errors.py
pymethyl2sam/core/genomics.py
pymethyl2sam/core/reference_genome.py
pymethyl2sam/core/sequencing.py
pymethyl2sam/io/__init__.py
pymethyl2sam/io/genome_loader.py
pymethyl2sam/simulator/__init__.py
pymethyl2sam/simulator/simulator.py
pymethyl2sam/simulator/summary.py
pymethyl2sam/utils/__init__.py
pymethyl2sam/utils/constants.py
pymethyl2sam/utils/logging.py
pymethyl2sam/utils/pysam.py
pymethyl2sam-0.1.2.dist-info/METADATA
pymethyl2sam-0.1.2.dist-info/WHEEL
pymethyl2sam-0.1.2.dist-info/top_level.txt
pymethyl2sam-0.1.2.dist-info/RECORD
