Metadata-Version: 2.4
Name: pymethyl2sam
Version: 0.1.2
Summary: Simulate DNA methylation and generate synthetic NGS reads with methylation tags.
Author-email: Yoni Weissler <yoni.weissler@gmail.com>
License: MIT
Project-URL: Homepage, https://github.com/yoni-w/pymethyl2sam
Project-URL: Repository, https://github.com/yoni-w/pymethyl2sam
Project-URL: Documentation, https://pymethyl2sam.readthedocs.io
Project-URL: Issues, https://github.com/yoni-w/pymethyl2sam/issues
Classifier: Development Status :: 3 - Alpha
Classifier: Intended Audience :: Science/Research
Classifier: License :: OSI Approved :: MIT License
Classifier: Programming Language :: Python :: 3
Classifier: Programming Language :: Python :: 3.9
Classifier: Programming Language :: Python :: 3.10
Classifier: Programming Language :: Python :: 3.11
Classifier: Programming Language :: Python :: 3.12
Classifier: Topic :: Scientific/Engineering :: Bio-Informatics
Classifier: Operating System :: POSIX :: Linux
Classifier: Operating System :: MacOS :: MacOS X
Requires-Python: >=3.9
Requires-Dist: pysam>=0.21.0
Requires-Dist: numpy>=1.21.0
Requires-Dist: pyyaml>=6.0
Requires-Dist: click>=8.0.0
Requires-Dist: typing-extensions>=4.0.0
Requires-Dist: importlib-metadata>=8.7.0
Provides-Extra: dev
Requires-Dist: pytest>=7.0.0; extra == "dev"
Requires-Dist: black>=23.0.0; extra == "dev"
Requires-Dist: pylint>=3.2.0; extra == "dev"
Requires-Dist: pre-commit>=3.2.0; extra == "dev"
Requires-Dist: sphinx>=6.0.0; extra == "dev"
Requires-Dist: sphinx-rtd-theme>=1.2.0; extra == "dev"
Requires-Dist: coverage[toml]>=7.0.0; extra == "dev"
